{
  "required": true,
  "minVersion": "0.8",
  "package": "com.iafenvoy.iafpatcher.mixin",
  "compatibilityLevel": "JAVA_8",
  "refmap": "iaf_patcher.refmap.json",
  "mixins": [
    "CitadelMixin",
    "EntityDragonBaseMixin",
    "EntityFireDragonMixin",
    "EntityIceDragonMixin",
    "EntityLightningDragonMixin",
    "memoryleak.DragonTabulaModelAnimatorFixMixin",
    "memoryleak.SeaSerpentTabulaModelAnimatorFixMixin"
  ],
  "client": [
    "ClientEventsMixin",
    "TitleScreenMixin",
    "memoryleak.BipedModelFixMixin",
    "memoryleak.NormalModelFixMixin"
  ],
  "injectors": {
    "defaultRequire": 1
  }
}
